{
  "id": "hoelderlin_1804",
  "title": "Hälfte des Lebens",
  "author": "Friedrich Hölderlin",
  "year": 1804,
  "context": {
    "historical": "Verfaßt an der Schwelle zu Hölderlins geistiger Umnachtung; existenzielle Krise; Vorahnung des eigenen inneren Verfalls; tiefmenschliches Artefakt der Endlichkeit; autobiografische Markierung einer Grenzsituation.",
    "emotional": [
      "Vorahnung",
      "Traurigkeit",
      "Endlichkeit",
      "Verzweiflung",
      "Melancholie",
      "Existenzielle Besorgnis"
    ]
  },
  "type": "human",
  "text": "Mit gelben Birnen hänget\nUnd voll mit wilden Rosen\nDas Land in den See,\nIhr holden Schwäne,\nUnd trunken von Küssen\nTunkt ihr das Haupt\nIns heilignüchterne Wasser.\n\nWeh mir, wo nehm ich, wenn\nEs Winter ist, die Blumen, und wo\nDen Sonnenschein\nUnd Schatten der Erde?\nDie Mauern stehn\nSprachlos und kalt, im Winde\nKlirren die Fahnen."
}
